py_netty/__init__.py
py_netty/bootstrap.py
py_netty/bytebuf.py
py_netty/channel.py
py_netty/eventfd.py
py_netty/eventloop.py
py_netty/handler.py
py_netty/utils.py
py_netty-1.0.8.dist-info/licenses/LICENSE
py_netty-1.0.8.dist-info/METADATA
py_netty-1.0.8.dist-info/WHEEL
py_netty-1.0.8.dist-info/top_level.txt
py_netty-1.0.8.dist-info/RECORD
